web_show/__init__.py
web_show/urls.py
web_show/views.py
web_show/templates/web_show/show.html
web_show-0.1.3.dist-info/METADATA
web_show-0.1.3.dist-info/WHEEL
web_show-0.1.3.dist-info/top_level.txt
web_show-0.1.3.dist-info/RECORD
